ec2imgutils/VERSION
ec2imgutils/__init__.py
ec2imgutils/ec2deprecateimg.py
ec2imgutils/ec2imgutils.py
ec2imgutils/ec2imgutilsExceptions.py
ec2imgutils/ec2listimg.py
ec2imgutils/ec2publishimg.py
ec2imgutils/ec2removeimg.py
ec2imgutils/ec2setup.py
ec2imgutils/ec2uploadimg.py
ec2imgutils/ec2utils.py
ec2imgutils-10.0.3.data/scripts/ec2deprecateimg
ec2imgutils-10.0.3.data/scripts/ec2listimg
ec2imgutils-10.0.3.data/scripts/ec2publishimg
ec2imgutils-10.0.3.data/scripts/ec2removeimg
ec2imgutils-10.0.3.data/scripts/ec2uploadimg
ec2imgutils-10.0.3.dist-info/LICENSE
ec2imgutils-10.0.3.dist-info/METADATA
ec2imgutils-10.0.3.dist-info/WHEEL
ec2imgutils-10.0.3.dist-info/top_level.txt
ec2imgutils-10.0.3.dist-info/RECORD
